librecommender-1.5.2.dist-info/RECORD
librecommender-1.5.2.dist-info/WHEEL
librecommender-1.5.2.dist-info/top_level.txt
librecommender-1.5.2.dist-info/METADATA
librecommender-1.5.2.dist-info/licenses/LICENSE
libserving/request.py
libserving/__init__.py
libserving/serialization/embed.py
libserving/serialization/online.py
libserving/serialization/tfmodel.py
libserving/serialization/__init__.py
libserving/serialization/common.py
libserving/serialization/redis.py
libserving/serialization/knn.py
libserving/sanic_serving/benchmark.py
libserving/sanic_serving/__init__.py
libserving/sanic_serving/online_deploy.py
libserving/sanic_serving/common.py
libserving/sanic_serving/knn_deploy.py
libserving/sanic_serving/embed_deploy.py
libserving/sanic_serving/tf_deploy.py
libreco/__init__.py
libreco/recommendation/preprocess.py
libreco/recommendation/__init__.py
libreco/recommendation/recommend.py
libreco/recommendation/cold_start.py
libreco/recommendation/ranking.py
libreco/torchops/configs.py
libreco/torchops/__init__.py
libreco/torchops/loss.py
libreco/torchops/rebuild.py
libreco/layers/attention.py
libreco/layers/convolutional.py
libreco/layers/embedding.py
libreco/layers/recurrent.py
libreco/layers/dense.py
libreco/layers/__init__.py
libreco/layers/activation.py
libreco/layers/transformer.py
libreco/layers/normalization.py
libreco/training/dispatch.py
libreco/training/__init__.py
libreco/training/torch_trainer.py
libreco/training/trainer.py
libreco/training/tf_trainer.py
libreco/prediction/preprocess.py
libreco/prediction/predict.py
libreco/prediction/__init__.py
libreco/graph/from_dgl.py
libreco/graph/__init__.py
libreco/graph/message.py
libreco/graph/inference.py
libreco/graph/neighbor_walk.py
libreco/algorithms/wave_net.py
libreco/algorithms/rnn4rec.py
libreco/algorithms/youtube_ranking.py
libreco/algorithms/sim.py
libreco/algorithms/swing.py
libreco/algorithms/item2vec.py
libreco/algorithms/_bpr.cpython-311-darwin.so
libreco/algorithms/_als.cpython-311-darwin.so
libreco/algorithms/ncf.py
libreco/algorithms/two_tower.py
libreco/algorithms/din.py
libreco/algorithms/wide_deep.py
libreco/algorithms/deepfm.py
