Metadata-Version: 2.4
Name: LibRecommender
Version: 1.5.2
Summary: Versatile end-to-end recommender system.
Home-page: https://github.com/massquantity/LibRecommender
Author: massquantity
Author-email: massquantity <jinxin_madie@163.com>
License: MIT
Project-URL: documentation, https://librecommender.readthedocs.io/en/latest/
Project-URL: repository, https://github.com/massquantity/LibRecommender
Keywords: Collaborative Filtering,Recommender System
Classifier: Development Status :: 5 - Production/Stable
Classifier: Intended Audience :: Developers
Classifier: Intended Audience :: Education
Classifier: Intended Audience :: Science/Research
Classifier: License :: OSI Approved :: MIT License
Classifier: Programming Language :: Python :: 3.6
Classifier: Programming Language :: Python :: 3.7
Classifier: Programming Language :: Python :: 3.8
Classifier: Programming Language :: Python :: 3.9
Classifier: Programming Language :: Python :: 3.10
Classifier: Programming Language :: Python :: 3.11
Classifier: Programming Language :: Cython
Classifier: Programming Language :: Rust
Requires-Python: >=3.6
License-File: LICENSE
Requires-Dist: gensim>=4.0.0
Requires-Dist: tqdm
Dynamic: author
Dynamic: home-page
Dynamic: license-file
